drf_mfcam/__init__.py
drf_mfcam/mixin.py
drf_mfcam-0.1a0.dist-info/LICENCE
drf_mfcam-0.1a0.dist-info/METADATA
drf_mfcam-0.1a0.dist-info/WHEEL
drf_mfcam-0.1a0.dist-info/top_level.txt
drf_mfcam-0.1a0.dist-info/RECORD
